{
    "targetAudience": {
      "title": "Who This Course Is For",
      "description": "Transform from writing custom code to building powerful automated solutions",
      "personas": [
        {
          "title": "Tech Leaders",
          "description": "Development managers ready to embrace automation-first approaches using n8n and AI",
          "icon": "Users"
        },
        {
          "title": "Developers",
          "description": "Developers looking to master n8n and automation tools instead of writing custom code",
          "icon": "Code"
        },
        {
          "title": "Solution Architects",
          "description": "Architects ready to design systems using n8n, automation tools, and AI integration",
          "icon": "Building"
        }
      ]
    },
    "transformationJourney": {
      "title": "Your Transformation Journey",
      "description": "A clear path from code-first to automation-first architecture",
      "stages": {
        "current": {
          "title": "Where You Are Now",
          "points": [
            "Writing custom code for every solution",
            "Maintaining complex codebases",
            "Long development cycles",
            "Limited automation implementation",
            "Minimal AI integration"
          ]
        },
        "future": {
          "title": "Where You'll Be",
          "points": [
            "Building solutions rapidly with n8n",
            "Creating complex workflows without code",
            "Integrating AI into automation flows",
            "Leading automation-first teams",
            "Delivering solutions in days, not months"
          ]
        }
      }
    },
    "businessImpact": {
      "title": "Business Impact",
      "description": "Measurable outcomes through automation",
      "impacts": [
        {
          "title": "Rapid Development",
          "description": "Build in days with n8n what used to take months with custom code",
          "metric": "10x faster"
        },
        {
          "title": "Reduced Maintenance",
          "description": "Less custom code means less maintenance and technical debt",
          "metric": "70% reduction"
        },
        {
          "title": "AI Integration",
          "description": "Seamlessly incorporate AI into your automation workflows",
          "metric": "100+ use cases"
        }
      ]
    },
    "corePhilosophy": {
      "title": "Core Philosophy",
      "description": "Foundational principles of automation-first development",
      "principles": [
        {
          "title": "Automation-First Mindset",
          "description": "Approach every challenge with n8n and automation tools before considering custom code",
          "icon": "Brain"
        },
        {
          "title": "Business Outcomes",
          "description": "Focus on rapid delivery and business value through automated solutions",
          "icon": "TrendingUp"
        },
        {
          "title": "Smart Integration",
          "description": "Build faster through intelligent combination of n8n, AI, and automation tools",
          "icon": "Layers"
        }
      ]
    }
}